power_platform_security_assessment/__init__.py
power_platform_security_assessment/base_classes.py
power_platform_security_assessment/consts.py
power_platform_security_assessment/environment_scanner.py
power_platform_security_assessment/security_assessment_tool.py
power_platform_security_assessment/token_manager.py
power_platform_security_assessment/utils.py
power_platform_security_assessment/fetchers/__init__.py
power_platform_security_assessment/fetchers/applications_fetcher.py
power_platform_security_assessment/fetchers/base_resource_fetcher.py
power_platform_security_assessment/fetchers/cloud_flows_fetcher.py
power_platform_security_assessment/fetchers/connections_fetcher.py
power_platform_security_assessment/fetchers/desktop_flows_fetcher.py
power_platform_security_assessment/fetchers/environments_fetcher.py
power_platform_security_assessment/fetchers/model_driven_apps_fetcher.py
power_platform_security_assessment/fetchers/users_fetcher.py
power_platform_security_assessment/report_builder/__init__.py
power_platform_security_assessment/report_builder/report.html
power_platform_security_assessment/report_builder/report_builder.py
power_platform_security_assessment/security_features/__init__.py
power_platform_security_assessment/security_features/common.py
power_platform_security_assessment/security_features/app_developers/__init__.py
power_platform_security_assessment/security_features/app_developers/app_developer_analyzer.py
power_platform_security_assessment/security_features/app_developers/app_developer_textual_report.py
power_platform_security_assessment/security_features/app_developers/model.py
power_platform_security_assessment/security_features/bypass_consent/__init__.py
power_platform_security_assessment/security_features/bypass_consent/bypass_concent_textual_report.py
power_platform_security_assessment/security_features/bypass_consent/bypass_consent_analyzer.py
power_platform_security_assessment/security_features/bypass_consent/model.py
power_platform_security_assessment-0.1.5.dist-info/METADATA
power_platform_security_assessment-0.1.5.dist-info/WHEEL
power_platform_security_assessment-0.1.5.dist-info/entry_points.txt
power_platform_security_assessment-0.1.5.dist-info/licenses/LICENSE
power_platform_security_assessment-0.1.5.dist-info/RECORD
