Metadata-Version: 2.4
Name: power-platform-security-assessment
Version: 0.1.5
Summary: Power Platform Security Assessment Tool
Project-URL: Homepage, https://github.com/Nokod/power-platform-security-assessment
Project-URL: Repository, https://github.com/Nokod/power-platform-security-assessment
Author-email: Nokod Security <support@nokodsecurity.com>
License: MIT
License-File: LICENSE
Classifier: License :: OSI Approved :: MIT License
Classifier: Operating System :: OS Independent
Classifier: Programming Language :: Python :: 3
Requires-Python: >=3.9
Requires-Dist: alive-progress~=3.1.5
Requires-Dist: jinja2~=3.1.4
Requires-Dist: msal~=1.28.1
Requires-Dist: pandas~=2.2.2
Requires-Dist: plotly~=5.24.0
Requires-Dist: pydantic~=2.8.2
Requires-Dist: pydash~=8.0.3
Requires-Dist: python-dateutil~=2.8.2
Requires-Dist: requests~=2.32.3
